{
    "tempo": "60",
    "notes": [{
        "note": "a4#",
        "duration": 0.642
    }, {
        "note": "c5",
        "duration": 0.651
    }, {
        "note": "d5#",
        "duration": 1.025
    }, {
        "note": "f5",
        "duration": 0.344
    }, {
        "note": "d5#",
        "duration": 0.315
    }, {
        "note": "f5",
        "duration": 0.292
    }, {
        "note": "d5#",
        "duration": 1.197
    }, {
        "note": "f5",
        "duration": 0.629
    }, {
        "note": "a5",
        "duration": 0.959
    }, {
        "note": "a5#",
        "duration": 0.315
    }, {
        "note": "a5",
        "duration": 0.289
    }, {
        "note": "a5#",
        "duration": 0.314
    }, {
        "note": "a5#",
        "duration": 1.972
    }, {
        "note": "c6",
        "duration": 0.311
    }, {
        "note": "a5#",
        "duration": 0.1
    }, {
        "note": "g5#",
        "duration": 0.1
    }, {
        "note": "g5",
        "duration": 0.1
    }, {
        "note": "g5#",
        "duration": 0.1
    }, {
        "note": "g5",
        "duration": 0.623
    }, {
        "note": "f5",
        "duration": 0.281
    }, {
        "note": "f5",
        "duration": 0.655
    }, {
        "note": "g5",
        "duration": 0.294
    }, {
        "note": "f5",
        "duration": 0.292
    }, {
        "note": "d5#",
        "duration": 0.062
    }, {
        "note": "d5",
        "duration": 0.11
    }, {
        "note": "d5#",
        "duration": 0.121
    }, {
        "note": "d5",
        "duration": 0.746
    }, {
        "note": "c5",
        "duration": 0.269
    }, {
        "note": "c5",
        "duration": 1.276
    }, {
        "note": "f5",
        "duration": 0.308
    }, {
        "note": "d5#",
        "duration": 0.3
    }, {
        "note": "f5",
        "duration": 0.265
    }, {
        "note": "d5",
        "duration": 0.29
    }, {
        "note": "c5",
        "duration": 0.311
    }, {
        "note": "d5",
        "duration": 0.57
    }, {
        "note": "a4#",
        "duration": 0.312
    }, {
        "note": "a4#",
        "duration": 2.737
    }, {
        "note": "c5",
        "duration": 0.562
    }, {
        "note": "d5#",
        "duration": 0.283
    }, {
        "note": "f5",
        "duration": 0.315
    }, {
        "note": "d5#",
        "duration": 0.271
    }, {
        "note": "f5",
        "duration": 0.285
    }, {
        "note": "f5",
        "duration": 0.988
    }, {
        "note": "g5#",
        "duration": 0.249
    }, {
        "note": "g5",
        "duration": 0.316
    }, {
        "note": "g5",
        "duration": 0.268
    }, {
        "note": "f5",
        "duration": 0.286
    }, {
        "note": "d5#",
        "duration": 0.815
    }, {
        "note": "f5",
        "duration": 0.606
    }, {
        "note": "a5",
        "duration": 0.937
    }, {
        "note": "a5#",
        "duration": 0.274
    }, {
        "note": "a5",
        "duration": 0.27
    }, {
        "note": "a5#",
        "duration": 0.284
    }, {
        "note": "d5#",
        "duration": 2.444
    }, {
        "note": "f5",
        "duration": 0.605
    }, {
        "note": "a5",
        "duration": 0.587
    }, {
        "note": "a5",
        "duration": 0.573
    }, {
        "note": "a5",
        "duration": 0.619
    }, {
        "note": "a5",
        "duration": 0.297
    }, {
        "note": "a5#",
        "duration": 0.296
    }, {
        "note": "a5",
        "duration": 0.287
    }, {
        "note": "a5#",
        "duration": 0.264
    }, {
        "note": "a5",
        "duration": 0.847
    }, {
        "note": "a5#",
        "duration": 0.311
    }, {
        "note": "a5",
        "duration": 1.219
    }, {
        "note": "a5",
        "duration": 0.61
    }, {
        "note": "a5",
        "duration": 0.328
    }, {
        "note": "a5#",
        "duration": 0.289
    }, {
        "note": "a5",
        "duration": 0.267
    }, {
        "note": "a5#",
        "duration": 0.289
    }, {
        "note": "a5",
        "duration": 0.597
    }, {
        "note": "a5#",
        "duration": 0.285
    }, {
        "note": "c6",
        "duration": 0.268
    }, {
        "note": "a5#",
        "duration": 0.255
    }, {
        "note": "g5#",
        "duration": 0.269
    }, {
        "note": "g5",
        "duration": 0.259
    }, {
        "note": "g5#",
        "duration": 0.27
    }, {
        "note": "g5",
        "duration": 0.262
    }, {
        "note": "g5",
        "duration": 0.28
    }, {
        "note": "f5",
        "duration": 0.247
    }, {
        "note": "c5",
        "duration": 1.236
    }, {
        "note": "c5",
        "duration": 0.286
    }, {
        "note": "d5#",
        "duration": 0.338
    }, {
        "note": "d5#",
        "duration": 0.28
    }, {
        "note": "d5",
        "duration": 0.265
    }, {
        "note": "c5",
        "duration": 0.285
    }, {
        "note": "c5",
        "duration": 0.837
    }, {
        "note": "g5#",
        "duration": 0.278
    }, {
        "note": "g5",
        "duration": 0.261
    }, {
        "note": "g5#",
        "duration": 0.302
    }, {
        "note": "g5",
        "duration": 0.28
    }, {
        "note": "f5",
        "duration": 0.261
    }, {
        "note": "g5",
        "duration": 0.575
    }, {
        "note": "f5",
        "duration": 0.297
    }, {
        "note": "d5#",
        "duration": 1.28
    }, {
        "note": "f5",
        "duration": 0.32
    }, {
        "note": "a5",
        "duration": 0.263
    }, {
        "note": "a5",
        "duration": 0.569
    }, {
        "note": "a5",
        "duration": 0.27
    }, {
        "note": "a5",
        "duration": 0.276
    }, {
        "note": "a5",
        "duration": 0.904
    }, {
        "note": "a5#",
        "duration": 0.287
    }, {
        "note": "a5",
        "duration": 0.271
    }, {
        "note": "a5#",
        "duration": 0.294
    }, {
        "note": "d5#",
        "duration": 1.216
    }, {
        "note": "f5",
        "duration": 0.601
    }, {
        "note": "a5",
        "duration": 0.911
    }, {
        "note": "a5#",
        "duration": 0.316
    }, {
        "note": "a5",
        "duration": 0.284
    }, {
        "note": "a5#",
        "duration": 0.287
    }, {
        "note": "d5#",
        "duration": 1.42
    }, {
        "note": "f5",
        "duration": 0.652
    }, {
        "note": "a5",
        "duration": 0.954
    }, {
        "note": "a5#",
        "duration": 0.305
    }, {
        "note": "a5",
        "duration": 0.25
    }, {
        "note": "a5#",
        "duration": 0.268
    }]
}
